clastic/__init__.py
clastic/_contextual_errors.py
clastic/_version.py
clastic/_werkzeug_serving.py
clastic/application.py
clastic/cline.py
clastic/decorators.py
clastic/errors.py
clastic/flaw.py
clastic/meta.py
clastic/meta_base.html
clastic/meta_env_section.html
clastic/meta_host_section.html
clastic/meta_main_base.html
clastic/meta_mw_section.html
clastic/meta_proc_section.html
clastic/meta_pyvm_section.html
clastic/meta_resource_section.html
clastic/meta_route_section.html
clastic/meta_rusage_section.html
clastic/route.py
clastic/server.py
clastic/sinter.py
clastic/static.py
clastic/utils.py
clastic/_clastic_assets/common.css
clastic/_clastic_assets/jquery-1.10.1.min.js
clastic/_clastic_assets/normalize.css
clastic/contrib/__init__.py
clastic/contrib/obj_browser.py
clastic/contrib/webtop/__init__.py
clastic/contrib/webtop/top.html
clastic/contrib/webtop/top.py
clastic/docs/routing.md
clastic/middleware/__init__.py
clastic/middleware/client_cache.py
clastic/middleware/compress.py
clastic/middleware/context.py
clastic/middleware/cookie.py
clastic/middleware/core.py
clastic/middleware/form.py
clastic/middleware/profile.py
clastic/middleware/stats.py
clastic/middleware/url.py
clastic/render/__init__.py
clastic/render/ashes_templates.py
clastic/render/chameleon_templates.py
clastic/render/mako_templates.py
clastic/render/simple.py
clastic/render/tabular.py
clastic/tests/__init__.py
clastic/tests/common.py
clastic/tests/test_arg_resolve.py
clastic/tests/test_ashes_render.py
clastic/tests/test_basic.py
clastic/tests/test_chameleon_render.py
clastic/tests/test_cline.py
clastic/tests/test_context_proc.py
clastic/tests/test_cookie.py
clastic/tests/test_decorators.py
clastic/tests/test_errors.py
clastic/tests/test_flaw.py
clastic/tests/test_http_routing.py
clastic/tests/test_mako_render.py
clastic/tests/test_meta.py
clastic/tests/test_middleware.py
clastic/tests/test_obj_browser.py
clastic/tests/test_render.py
clastic/tests/test_render_error.py
clastic-24.0.0.dist-info/LICENSE
clastic-24.0.0.dist-info/METADATA
clastic-24.0.0.dist-info/WHEEL
clastic-24.0.0.dist-info/top_level.txt
clastic-24.0.0.dist-info/RECORD
